pysecretserver/__init__.py
pysecretserver/api.py
pysecretserver/items.py
pysecretserver/query.py
pysecretserver-0.4.2.dist-info/LICENSE
pysecretserver-0.4.2.dist-info/METADATA
pysecretserver-0.4.2.dist-info/WHEEL
pysecretserver-0.4.2.dist-info/top_level.txt
pysecretserver-0.4.2.dist-info/RECORD
